optimake/__init__.py
optimake/cli.py
optimake/config.py
optimake/convert.py
optimake/logger.py
optimake/parsers.py
optimake/serve.py
optimake/archive/__init__.py
optimake/archive/archive_record.py
optimake/archive/cli.py
optimake/archive/scan_records.py
optimake/archive/utils.py
optimake-0.2.2.dist-info/LICENSE
optimake-0.2.2.dist-info/METADATA
optimake-0.2.2.dist-info/WHEEL
optimake-0.2.2.dist-info/entry_points.txt
optimake-0.2.2.dist-info/top_level.txt
optimake-0.2.2.dist-info/RECORD
