Metadata-Version: 2.1
Name: optimake
Version: 0.2.2
Summary: Tools for making OPTIMADE APIs from raw structural data.
Requires-Python: >=3.10
License-File: LICENSE
Requires-Dist: pydantic ~=2.2
Requires-Dist: optimade[ase,server] ~=1.1
Requires-Dist: pyyaml ~=6.0
Requires-Dist: pymatgen >=2023.9
Requires-Dist: pandas ~=2.1
Requires-Dist: pybtex ~=0.24
Requires-Dist: tqdm ~=4.65
Requires-Dist: requests ~=2.31
Requires-Dist: numpy ~=1.26
Requires-Dist: click ~=8.1
Provides-Extra: dev
Requires-Dist: black ; extra == 'dev'
Requires-Dist: ruff ; extra == 'dev'
Requires-Dist: pre-commit ; extra == 'dev'
Requires-Dist: mypy ; extra == 'dev'
Requires-Dist: isort ; extra == 'dev'
Requires-Dist: types-all ; extra == 'dev'
Provides-Extra: tests
Requires-Dist: pytest ~=7.4 ; extra == 'tests'
Requires-Dist: pytest-cov ~=4.0 ; extra == 'tests'
